{
    "sourceFile": "js/games/fire_manifest.js",
    "activeCommit": 0,
    "commits": [
        {
            "activePatchIndex": 1,
            "patches": [
                {
                    "date": 1778516131264,
                    "content": "Index: \n===================================================================\n--- \n+++ \n"
                },
                {
                    "date": 1778516914847,
                    "content": "Index: \n===================================================================\n--- \n+++ \n@@ -1,279 +1,258 @@\n /**\r\n- * 시현이 놀이터 OS — 긴급출동! 초강력 소방대 V8 (Ultimate Master Edition)\r\n- * 업데이트: V7 피드백 완벽 반영 (반응형 간격, 모바일 파티클 최적화, 상태 초기화 픽스)\r\n+ * 시현이 놀이터 OS — 초강력 소방대 V14 (Full Feature Edition)\r\n+ * [업데이트] 18종 풀로드, 3가지 모드(4/9/16), 물대포 VFX 복구, 타겟 글로우, 엔딩, 이미지 폴백 완비\r\n  */\r\n \r\n (function () {\r\n-  const GAME_KEY = 'megaDispatchV8';\r\n-  const STYLE_ID = 'sihyeon-mega-v8-style';\r\n-  const FIRE_DATA = './assets/vehicles/fire_manifest.json'; \r\n+  const GAME_KEY = 'megaDispatchV14';\r\n+  const STYLE_ID = 'sihyeon-mega-v14-style';\r\n+  const MANIFESTS = {\r\n+    normal: './assets/vehicles/fire_manifest.json',\r\n+    special: './assets/vehicles/fire_special_manifest.json'\r\n+  };\r\n \r\n   const state = {\r\n     container: null,\r\n     options: {},\r\n     allTrucks: [],\r\n+    displayTrucks: [],\r\n     mission: [],\r\n     currentLevel: 1, \r\n     userIndex: 0,\r\n     combo: 0,\r\n+    gridSize: 9, \r\n     isBusy: false,\r\n+    gameStarted: false,\r\n     destroyed: false\r\n   };\r\n \r\n   const ROLE_ICONS = {\r\n-    pump_engine: '💧', water_tanker: '💧', airport_crash_tender: '💧', foam_tender: '💧',\r\n-    ladder_truck: '🪜', aerial_ladder_truck: '🪜', articulating_ladder_truck: '🪜',\r\n-    rescue_fire_truck: '⛑️', fire_command_car: '📢'\r\n+    pump_engine: '💧', water_tanker: '💧', ladder_truck: '🪜', \r\n+    aerial_ladder_truck: '🪜', articulating_ladder_truck: '🪜', \r\n+    rescue_fire_truck: '⛑️', airport_fire_truck: '✈️', \r\n+    foam_fire_truck: '🫧', fire_command_vehicle: '📢',\r\n+    fire_tank: '🚜', airport_crash_tender: '💧', \r\n+    wildfire_6x6_truck: '🌲', robot_demolition_fire_vehicle: '🤖', \r\n+    smoke_extraction_fan_truck: '🌀', articulating_boom_truck: '🦾', \r\n+    fire_command_suv: '📢'\r\n   };\r\n \r\n   function injectStyle() {\r\n     if (document.getElementById(STYLE_ID)) return;\r\n     const s = document.createElement('style');\r\n     s.id = STYLE_ID;\r\n     s.textContent = `\r\n-      .md8-root {\r\n-        width: 100%; height: 100%; display: flex; flex-direction: column;\r\n-        background: #050505; position: relative; overflow: hidden;\r\n-        font-family: 'Jua', sans-serif;\r\n-      }\r\n+      .md14-root { width: 100%; height: 100%; display: flex; flex-direction: column; background: #050505; position: relative; overflow: hidden; font-family: 'Jua', sans-serif; }\r\n       \r\n-      .md8-city-bg {\r\n-        position: absolute; inset: 0; background: linear-gradient(rgba(0,0,0,0.4), rgba(0,0,0,0.4)), url('./assets/games/dispatch/city_night.webp') center bottom / cover;\r\n-        opacity: 0.7; z-index: 1; pointer-events: none;\r\n-      }\r\n+      /* [배경] 도시 & 불꽃 */\r\n+      .md14-city-bg { position: absolute; inset: 0; background: linear-gradient(rgba(0,0,0,0.5), rgba(0,0,0,0.5)), url('./assets/games/dispatch/city_night.webp') center bottom / cover; opacity: 0.7; z-index: 1; pointer-events: none; }\r\n+      .md14-fire-overlay { position: absolute; bottom: 0; left: 0; width: 100%; height: 45%; background: linear-gradient(transparent, rgba(255, 80, 0, 0.3)); z-index: 2; pointer-events: none; animation: md14Fire 3s infinite alternate; }\r\n+      @keyframes md14Fire { from { opacity: 0.2; } to { opacity: 0.5; } }\r\n \r\n-      /* [수정] 배경 불 효과 & 애니메이션 */\r\n-      .md8-fire-overlay {\r\n-        position: absolute; bottom: 0; left: 0; width: 100%; height: 45%;\r\n-        background: linear-gradient(transparent, rgba(255, 80, 0, 0.25));\r\n-        z-index: 2; pointer-events: none; animation: subtleFire 3s infinite alternate;\r\n-      }\r\n-      @keyframes subtleFire { from { opacity: 0.25; } to { opacity: 0.55; } }\r\n+      /* [그리드] 가구 바닥 장식 */\r\n+      .md14-garage { flex: 1; display: grid; gap: 12px; padding: 15px; z-index: 10; align-content: center; position: relative; }\r\n+      .md14-garage::before { content: ''; position: absolute; inset: 0; background: repeating-linear-gradient(90deg, transparent, transparent 40px, rgba(255,255,255,0.05) 40px, rgba(255,255,255,0.05) 42px); z-index: -1; }\r\n+      .grid-4 { grid-template-columns: repeat(2, 1fr); padding: 30px; gap: 25px; }\r\n+      .grid-9 { grid-template-columns: repeat(3, 1fr); }\r\n+      .grid-16 { grid-template-columns: repeat(4, 1fr); gap: 10px; }\r\n \r\n-      /* [수정] 헤더: clamp를 이용한 반응형 간격 처리 */\r\n-      .md8-header { \r\n-        position: relative; z-index: 10; min-height: 140px;\r\n-        background: rgba(0,0,0,0.8); display: flex; align-items: center; justify-content: center; \r\n-        gap: clamp(12px, 3vw, 28px); border-bottom: 6px solid #ff1744; padding: 10px;\r\n-      }\r\n+      /* [헤더] 중앙 집중 프리뷰 */\r\n+      .md14-header { position: relative; z-index: 10; height: clamp(140px, 20vh, 180px); background: rgba(0,0,0,0.8); display: flex; align-items: center; justify-content: center; gap: 15px; border-bottom: 6px solid #ff1744; }\r\n+      .md-mission-card { width: 70px; height: 70px; background: #fff; border-radius: 18px; display: flex; align-items: center; justify-content: center; border: 4px solid #fff; position: relative; transition: all 0.3s; }\r\n+      .md-mission-card.preview-large { width: clamp(110px, 25vw, 150px); height: clamp(110px, 25vw, 150px); border-color: #ffeb3b; box-shadow: 0 0 25px #ffeb3b; }\r\n+      .md-mission-card img { width: 85%; height: 85%; object-fit: contain; }\r\n+      .md-mission-card.done { opacity: 0.2; filter: grayscale(100%); }\r\n \r\n-      /* [수정] 미션 카드 & 이미지 최적화 */\r\n-      .md-mission-card {\r\n-        width: clamp(70px, 15vw, 100px); height: clamp(70px, 15vw, 100px);\r\n-        background: #fff; border-radius: 22px; display: flex; align-items: center; justify-content: center;\r\n-        border: 5px solid #fff; position: relative; transition: all 0.4s cubic-bezier(0.175, 0.885, 0.32, 1.275);\r\n-      }\r\n-      .md-mission-card img { width: 82%; height: 82%; object-fit: contain; }\r\n-      .md-mission-card.active { border-color: #ffeb3b; transform: scale(1.25) rotate(5deg); box-shadow: 0 0 30px #ffeb3b; }\r\n-      .md-mission-card.done { opacity: 0.25; filter: grayscale(100%); transform: scale(0.8); }\r\n-\r\n-      .md-role-tag { font-size: 16px; position: absolute; top: -12px; right: -12px; background: #fff; border-radius: 50%; width: 30px; height: 30px; display: grid; place-items: center; box-shadow: 0 2px 5px rgba(0,0,0,0.3); z-index:5; }\r\n-\r\n-      .md8-level-badge { position: absolute; top: 15px; left: 20px; background: #ff1744; color: #fff; padding: 5px 15px; border-radius: 15px; font-size: clamp(18px, 4vw, 24px); font-weight: 900; z-index: 100; border: 3px solid #fff; }\r\n-\r\n-      .md8-garage { flex: 1; display: grid; grid-template-columns: repeat(3, 1fr); gap: 15px; padding: 20px; z-index: 10; align-content: center; }\r\n-      .md8-truck-btn { aspect-ratio: 1/1; background: #fff; border-radius: 25px; border: none; box-shadow: 0 10px 0 #888; display: flex; align-items: center; justify-content: center; position: relative; transition: transform 0.1s; overflow: visible; }\r\n-      .md8-truck-btn img { width: 95%; height: 95%; object-fit: contain; }\r\n+      /* [버튼] 48dp+ 확보 & 타겟 글로우 */\r\n+      .md14-truck-btn { aspect-ratio: 1/1; background: #fff; border-radius: 20px; border: none; box-shadow: 0 8px 0 #888; display: flex; align-items: center; justify-content: center; padding: 10px; min-height: 80px; position: relative; transition: transform 0.1s; }\r\n+      .md14-truck-btn img { width: 90%; height: 90%; object-fit: contain; }\r\n+      .md14-truck-btn.target-glow { box-shadow: 0 0 20px #ffeb3b, inset 0 0 10px #fff; animation: mdGlow 1.5s infinite; }\r\n+      @keyframes mdGlow { 0%, 100% { opacity: 1; transform: scale(1); } 50% { opacity: 0.8; transform: scale(1.02); } }\r\n       \r\n-      .md8-spotlight { position: absolute; inset: -10%; background: radial-gradient(circle, rgba(255,255,255,0.5) 0%, transparent 70%); opacity: 0; transition: opacity 0.2s; pointer-events: none; }\r\n-      .md8-truck-btn.touch-active .md8-spotlight { opacity: 1; }\r\n-      .md8-truck-btn.touch-active { transform: translateY(8px); box-shadow: 0 2px 0 #888; }\r\n-\r\n-      /* [복구] 쉐이크 애니메이션 */\r\n-      .md-shake { animation: mdShake 0.45s linear; }\r\n-      @keyframes mdShake {\r\n-        0%, 100% { transform: translateX(0); }\r\n-        10%, 30%, 50%, 70%, 90% { transform: translateX(-8px); }\r\n-        20%, 40%, 60%, 80% { transform: translateX(8px); }\r\n-      }\r\n-\r\n-      /* [수정] 엔딩 화면 버튼 최적화 */\r\n-      #restartBtn { min-width: 220px; margin-top: 20px; padding: 15px 40px; font-size: 24px; border-radius: 30px; background: #ff1744; color: #fff; border: none; box-shadow: 0 8px 0 #b71c1c; font-weight: 900; }\r\n-\r\n+      .md-shake { animation: mdShakeAnim 0.45s linear; }\r\n+      @keyframes mdShakeAnim { 0%, 100% { transform: translateX(0); } 10%, 30%, 50%, 70%, 90% { transform: translateX(-10px); } 20%, 40%, 60%, 80% { transform: translateX(10px); } }\r\n       .water-drop { position: absolute; width: 14px; height: 14px; background: #4fc3f7; border-radius: 50%; pointer-events: none; z-index: 1000; animation: waterFly 0.7s ease-out forwards; }\r\n       @keyframes waterFly { to { transform: translate(var(--tx), var(--ty)) scale(0); opacity: 0; } }\r\n \r\n-      @media (min-width: 768px) {\r\n-        .md8-garage { gap: 30px; padding: 40px; max-width: 900px; margin: 0 auto; }\r\n-        .md8-header { min-height: 180px; gap: 30px; }\r\n-      }\r\n+      .md14-start-screen { position: absolute; inset: 0; z-index: 1000; background: rgba(0,0,0,0.95); display: flex; flex-direction: column; align-items: center; justify-content: center; color: white; text-align: center; }\r\n+      .mode-btn { padding: 15px 30px; font-size: 22px; border-radius: 20px; border: none; background: #ff1744; color: white; box-shadow: 0 6px 0 #b71c1c; margin: 10px; font-weight: 900; }\r\n     `;\r\n     document.head.appendChild(s);\r\n   }\r\n \r\n-  /* [수정] 모바일 파티클 최적화 */\r\n-  function shootWater(x, y, isSuper = false) {\r\n-    const isMobile = window.innerWidth < 768;\r\n-    const count = isSuper ? (isMobile ? 22 : 35) : (isMobile ? 12 : 18);\r\n-    for (let i = 0; i < count; i++) {\r\n-      const drop = document.createElement('div');\r\n-      drop.className = 'water-drop';\r\n-      drop.style.left = x + 'px'; drop.style.top = y + 'px';\r\n-      drop.style.setProperty('--tx', (Math.random() * (isSuper ? 400 : 200) - (isSuper ? 200 : 100)) + 'px');\r\n-      drop.style.setProperty('--ty', (Math.random() * -300 - 50) + 'px');\r\n-      state.container.appendChild(drop);\r\n-      setTimeout(() => drop.remove(), 700);\r\n+  async function loadAllTrucks() {\r\n+    if (state.allTrucks.length > 0) return;\r\n+    try {\r\n+      const [res1, res2] = await Promise.all([\r\n+        fetch(MANIFESTS.normal).then(r => r.json()),\r\n+        fetch(MANIFESTS.special).then(r => r.json())\r\n+      ]);\r\n+      const list1 = res1.map(t => ({ ...t, gameId: `n_${t.id}` }));\r\n+      const list2 = res2.map(t => ({ ...t, gameId: `s_${t.id}` }));\r\n+      state.allTrucks = [...list1, ...list2];\r\n+    } catch (e) {\r\n+      state.allTrucks = [{ gameId: 'n_pump', id: 'pump_engine', file: 'assets/vehicles/fire/pump_engine.png', name_ko: '펌프차' }];\r\n     }\r\n   }\r\n \r\n+  function showModeSelection() {\r\n+    state.container.innerHTML = `\r\n+      <div class=\"md14-root\">\r\n+        <div class=\"md14-city-bg\"></div>\r\n+        <div class=\"md14-start-screen\">\r\n+          <h1 style=\"font-size: 36px; color: #ffeb3b;\">본부장 시현! 출동 준비!</h1>\r\n+          <div>\r\n+            <button class=\"mode-btn\" onclick=\"window.setV14Mode(4)\">쉬움 🚒 (4대)</button>\r\n+            <button class=\"mode-btn\" onclick=\"window.setV14Mode(9)\">보통 🚒🚒 (9대)</button>\r\n+            <button class=\"mode-btn\" onclick=\"window.setV14Mode(16)\">도전 🚒🚒🚒 (16대)</button>\r\n+          </div>\r\n+        </div>\r\n+      </div>\r\n+    `;\r\n+  }\r\n+\r\n+  window.setV14Mode = (size) => {\r\n+    state.gridSize = size;\r\n+    state.gameStarted = true;\r\n+    startRound();\r\n+  };\r\n+\r\n   async function startRound() {\r\n-    if (state.destroyed) return;\r\n-    \r\n-    // [수정] 안전한 상태 초기화\r\n+    if (state.destroyed || !state.gameStarted) return;\r\n+    await loadAllTrucks();\r\n     state.isBusy = false;\r\n     state.userIndex = 0;\r\n+    state.combo = 0;\r\n \r\n-    if (state.allTrucks.length === 0) {\r\n-      const res = await fetch(FIRE_DATA); \r\n-      state.allTrucks = await res.json();\r\n-    }\r\n-    const missionCount = Math.min(state.currentLevel + 1, 5);\r\n-    state.mission = [...state.allTrucks].sort(() => 0.5 - Math.random()).slice(0, missionCount);\r\n+    // 18종 중 그리드 크기만큼 랜덤 배치\r\n+    state.displayTrucks = [...state.allTrucks].sort(() => 0.5 - Math.random()).slice(0, state.gridSize);\r\n     \r\n+    // 미션 생성 (그리드에 따라 개수 조정)\r\n+    const mCount = state.gridSize === 4 ? 2 : (state.gridSize === 9 ? 3 : 4);\r\n+    state.mission = [...state.displayTrucks].sort(() => 0.5 - Math.random()).slice(0, Math.min(mCount + Math.floor(state.currentLevel/3), state.gridSize));\r\n+    \r\n     render();\r\n-\r\n-    // [복구] 시작 음성 가이드\r\n-    if (state.options.speakGuide) {\r\n-      state.options.speakGuide(`레벨 ${state.currentLevel}! 순서대로 출동하자!`, true);\r\n-    }\r\n+    updateTargetGlow();\r\n   }\r\n \r\n   function render() {\r\n-    if (state.destroyed || !state.container) return;\r\n+    if (!state.gameStarted) return;\r\n     state.container.innerHTML = `\r\n-      <div class=\"md8-root\">\r\n-        <div class=\"md8-city-bg\"></div>\r\n-        <div class=\"md8-fire-overlay\"></div>\r\n-        <div class=\"md8-level-badge\">LEVEL ${state.currentLevel}</div>\r\n-        <div class=\"md8-header\">\r\n+      <div class=\"md14-root\">\r\n+        <div class=\"md14-city-bg\"></div>\r\n+        <div class=\"md14-fire-overlay\"></div>\r\n+        <div class=\"md14-level-badge\" style=\"position:absolute; top:15px; left:20px; color:#fff; font-size:20px; font-weight:900; z-index:100;\">🚒 ${state.currentLevel} 🚒</div>\r\n+        <div class=\"md14-header\">\r\n           ${state.mission.map((m, i) => `\r\n-            <div class=\"md-mission-card ${i === state.userIndex ? 'active' : (i < state.userIndex ? 'done' : '')}\">\r\n-              <div class=\"md-role-tag\">${ROLE_ICONS[m.id] || '🚒'}</div>\r\n-              <img src=\"${m.file}\">\r\n+            <div class=\"md-mission-card ${i === state.userIndex ? 'preview-large active' : (i < state.userIndex ? 'done' : '')}\">\r\n+              <div style=\"font-size:14px; position:absolute; top:-8px; right:-8px; background:#fff; border-radius:50%; width:24px; height:24px; display:grid; place-items:center; color:#000; box-shadow:0 2px 4px #000;\">${ROLE_ICONS[m.id] || '🚒'}</div>\r\n+              <img src=\"${m.file}\" onerror=\"this.src='./assets/default-truck.png'; this.style.background='linear-gradient(45deg, #ff6b6b, #4ecdc4)';\">\r\n             </div>\r\n-          `).join(' <span style=\"color:#fff; font-size:24px;\">▶</span> ')}\r\n+          `).join('')}\r\n         </div>\r\n-        <div class=\"md8-garage\">\r\n-          ${state.allTrucks.slice(0, 9).map(t => `\r\n-            <button class=\"md8-truck-btn\" data-id=\"${t.id}\">\r\n-              <div class=\"md8-spotlight\"></div>\r\n-              <img src=\"${t.file}\">\r\n+        <div class=\"md14-garage grid-${state.gridSize}\">\r\n+          ${state.displayTrucks.map(t => `\r\n+            <button class=\"md14-truck-btn\" data-game-id=\"${t.gameId}\">\r\n+              <img src=\"${t.file}\" onerror=\"this.src='./assets/default-truck.png'; this.style.background='linear-gradient(45deg, #ff6b6b, #4ecdc4)';\">\r\n             </button>\r\n           `).join('')}\r\n         </div>\r\n       </div>\r\n     `;\r\n-    state.container.querySelectorAll('.md8-truck-btn').forEach(btn => {\r\n-      btn.onclick = (e) => handleTouch(btn.dataset.id, btn, e);\r\n+    state.container.querySelectorAll('.md14-truck-btn').forEach(btn => {\r\n+      btn.onclick = (e) => handleTouch(btn.dataset.gameId, btn, e);\r\n     });\r\n   }\r\n \r\n-  function handleTouch(id, el, e) {\r\n-    if (state.isBusy || state.destroyed) return;\r\n+  function updateTargetGlow() {\r\n+    const targetId = state.mission[state.userIndex]?.gameId;\r\n+    state.container.querySelectorAll('.md14-truck-btn').forEach(btn => {\r\n+      btn.classList.remove('target-glow');\r\n+      if (btn.dataset.gameId === targetId) btn.classList.add('target-glow');\r\n+    });\r\n+  }\r\n \r\n-    el.classList.add('touch-active');\r\n-    setTimeout(() => el.classList.remove('touch-active'), 280);\r\n+  function shootWater(x, y, isSuper) {\r\n+    const count = isSuper ? 30 : 15;\r\n+    for (let i = 0; i < count; i++) {\r\n+      const drop = document.createElement('div');\r\n+      drop.className = 'water-drop';\r\n+      drop.style.left = x + 'px'; drop.style.top = y + 'px';\r\n+      drop.style.setProperty('--tx', (Math.random() * (isSuper ? 400 : 200) - (isSuper ? 200 : 100)) + 'px');\r\n+      drop.style.setProperty('--ty', (Math.random() * -300 - 50) + 'px');\r\n+      state.container.appendChild(drop);\r\n+      setTimeout(() => drop.remove(), 700);\r\n+    }\r\n+  }\r\n \r\n+  function handleTouch(gameId, el, e) {\r\n+    if (state.isBusy) return;\r\n     const target = state.mission[state.userIndex];\r\n+    const root = state.container.querySelector('.md14-root');\r\n \r\n-    if (id === target.id) {\r\n+    if (gameId === target.gameId) {\r\n       state.userIndex++;\r\n       state.combo++;\r\n-      const isSuper = state.combo >= 2; // [수정] 4살 추천 밸런스\r\n+      const isSuper = state.combo >= 2;\r\n+      \r\n+      // [복구] 물대포 VFX 발사\r\n       shootWater(e.clientX, e.clientY, isSuper);\r\n-      if (navigator.vibrate) navigator.vibrate(isSuper ? 150 : 80);\r\n+      \r\n+      el.style.transform = 'scale(1.3) !important';\r\n+      setTimeout(() => el.style.transform = '', 300);\r\n \r\n-      const msg = isSuper ? \"초강력!! \" : \"\";\r\n       if (state.options.speakGuide) {\r\n-        state.options.speakGuide(`${msg}${target.name_ko} 출동! ${target.sound_ko || ''}`, true);\r\n+        const msg = isSuper ? \"초강력!! \" : \"\";\r\n+        state.options.speakGuide(`${msg}${target.name_ko} 출동!`, true);\r\n       }\r\n       \r\n       if (state.userIndex >= state.mission.length) {\r\n         state.isBusy = true;\r\n         setTimeout(finishRound, 700);\r\n       } else {\r\n-        setTimeout(render, 550);\r\n+        render();\r\n+        updateTargetGlow();\r\n       }\r\n     } else {\r\n       state.combo = 0;\r\n-      if (state.options.speakGuide) state.options.speakGuide(\"아니야! 다시 봐보자!\", true);\r\n-      if (navigator.vibrate) navigator.vibrate([40, 60, 40]);\r\n-      \r\n-      const root = state.container.querySelector('.md8-root');\r\n-      if (root) {\r\n-        root.classList.add('md-shake');\r\n-        setTimeout(() => root.classList.remove('md-shake'), 450);\r\n-      }\r\n+      if (root) { root.classList.add('md-shake'); setTimeout(() => root.classList.remove('md-shake'), 450); }\r\n+      if (state.options.speakGuide) state.options.speakGuide(\"다시 골라보자!\", true);\r\n     }\r\n   }\r\n \r\n-  /* [수정] 명시적 상태 관리 및 애니메이션 최적화 */\r\n   function finishRound() {\r\n-    if (state.destroyed) return;\r\n+    if (state.options.fireConfetti) state.options.fireConfetti();\r\n     \r\n-    state.combo = 0;\r\n-    state.isBusy = true; \r\n-    \r\n-    if (state.options.fireConfetti) state.options.fireConfetti();\r\n-    if (state.options.gainExp) state.options.gainExp(25 + state.currentLevel * 18);\r\n+    // [보충] 성공 시 골드 장식\r\n+    state.container.querySelectorAll('.md14-truck-btn').forEach(btn => {\r\n+      btn.style.background = 'linear-gradient(45deg, gold, #ff1744)';\r\n+    });\r\n \r\n-    const clearedLevel = state.currentLevel;\r\n-\r\n-    if (clearedLevel === 8) {\r\n-        showEnding();\r\n-        return;\r\n+    if (state.currentLevel >= 8) {\r\n+      showEnding();\r\n+      return;\r\n     }\r\n \r\n     state.currentLevel++;\r\n-    if (state.options.speakGuide) {\r\n-      state.options.speakGuide(`와아아! ${clearedLevel}레벨 클리어!! 다음 레벨 출동!`, true);\r\n-    }\r\n-\r\n-    const trucks = state.container.querySelectorAll('.md8-truck-btn');\r\n-    trucks.forEach((btn, i) => {\r\n-      setTimeout(() => {\r\n-        btn.style.transition = '1.05s cubic-bezier(0.55, 0, 1, 1)';\r\n-        btn.style.transform = 'translateX(200vw) scale(1.55) rotate(22deg)';\r\n-      }, i * 70);\r\n-    });\r\n-\r\n-    setTimeout(startRound, 2750);\r\n+    setTimeout(startRound, 2500);\r\n   }\r\n \r\n-  /* [수정] 엔딩 후 재시작 로직 강화 */\r\n   function showEnding() {\r\n-    state.isBusy = true;\r\n-    state.combo = 0;\r\n     state.container.innerHTML = `\r\n-      <div class=\"md8-root\" style=\"justify-content:center; align-items:center; text-align:center; color:#fff;\">\r\n-        <div class=\"md8-city-bg\"></div>\r\n-        <div style=\"z-index:100;\">\r\n-          <h1 style=\"font-size: clamp(32px, 8vw, 52px); color: gold; text-shadow:0 0 30px red;\">🏆 전설의 시현 본부장 🏆</h1>\r\n-          <p style=\"font-size: clamp(18px, 4vw, 26px);\">시현이가 모든 불을 다 껐어요!</p>\r\n-          <div style=\"font-size: 80px; margin: 20px 0;\">🚒🔥🚑🚓</div>\r\n-          <button id=\"restartBtn\">다시 출동! 🔄</button>\r\n+      <div class=\"md14-root\">\r\n+        <div class=\"md14-city-bg\"></div>\r\n+        <div class=\"md14-start-screen\">\r\n+          <h1 style=\"font-size: 48px; color: gold; text-shadow: 0 0 20px red;\">👑 전설의 본부장 시현 👑</h1>\r\n+          <p style=\"font-size: 24px; margin: 20px 0;\">시현이가 마을을 지켜냈어요!</p>\r\n+          <button class=\"mode-btn\" style=\"font-size:32px;\" onclick=\"location.reload()\">출동! 🔄</button>\r\n         </div>\r\n       </div>\r\n     `;\r\n-    if (state.options.speakGuide) state.options.speakGuide(\"시현 본부장님 만세! 당신은 최고의 소방 영웅입니다!\", true);\r\n-    \r\n-    document.getElementById('restartBtn').onclick = () => { \r\n-      state.currentLevel = 1; \r\n-      state.combo = 0;\r\n-      state.isBusy = false;\r\n-      startRound(); \r\n-    };\r\n+    if (state.options.speakGuide) state.options.speakGuide(\"시현 본부장님 만세! 모든 미션을 완료했습니다!\", true);\r\n   }\r\n \r\n-  function destroy() {\r\n-    state.destroyed = true;\r\n-    if (state.container) state.container.innerHTML = '';\r\n-    state.container = null;\r\n-  }\r\n-\r\n-  window.SihyeonGames = window.SihyeonGames || {};\r\n   window.SihyeonGames[GAME_KEY] = { \r\n-    render: (c, o) => { state.container=c; state.options=o; state.destroyed=false; injectStyle(); startRound(); }, \r\n-    destroy \r\n+    render: (c, o) => { state.container=c; state.options=o; injectStyle(); showModeSelection(); }, \r\n+    destroy: () => { state.destroyed = true; }\r\n   };\r\n })();\n\\ No newline at end of file\n"
                }
            ],
            "date": 1778516131264,
            "name": "Commit-0",
            "content": "/**\r\n * 시현이 놀이터 OS — 긴급출동! 초강력 소방대 V8 (Ultimate Master Edition)\r\n * 업데이트: V7 피드백 완벽 반영 (반응형 간격, 모바일 파티클 최적화, 상태 초기화 픽스)\r\n */\r\n\r\n(function () {\r\n  const GAME_KEY = 'megaDispatchV8';\r\n  const STYLE_ID = 'sihyeon-mega-v8-style';\r\n  const FIRE_DATA = './assets/vehicles/fire_manifest.json'; \r\n\r\n  const state = {\r\n    container: null,\r\n    options: {},\r\n    allTrucks: [],\r\n    mission: [],\r\n    currentLevel: 1, \r\n    userIndex: 0,\r\n    combo: 0,\r\n    isBusy: false,\r\n    destroyed: false\r\n  };\r\n\r\n  const ROLE_ICONS = {\r\n    pump_engine: '💧', water_tanker: '💧', airport_crash_tender: '💧', foam_tender: '💧',\r\n    ladder_truck: '🪜', aerial_ladder_truck: '🪜', articulating_ladder_truck: '🪜',\r\n    rescue_fire_truck: '⛑️', fire_command_car: '📢'\r\n  };\r\n\r\n  function injectStyle() {\r\n    if (document.getElementById(STYLE_ID)) return;\r\n    const s = document.createElement('style');\r\n    s.id = STYLE_ID;\r\n    s.textContent = `\r\n      .md8-root {\r\n        width: 100%; height: 100%; display: flex; flex-direction: column;\r\n        background: #050505; position: relative; overflow: hidden;\r\n        font-family: 'Jua', sans-serif;\r\n      }\r\n      \r\n      .md8-city-bg {\r\n        position: absolute; inset: 0; background: linear-gradient(rgba(0,0,0,0.4), rgba(0,0,0,0.4)), url('./assets/games/dispatch/city_night.webp') center bottom / cover;\r\n        opacity: 0.7; z-index: 1; pointer-events: none;\r\n      }\r\n\r\n      /* [수정] 배경 불 효과 & 애니메이션 */\r\n      .md8-fire-overlay {\r\n        position: absolute; bottom: 0; left: 0; width: 100%; height: 45%;\r\n        background: linear-gradient(transparent, rgba(255, 80, 0, 0.25));\r\n        z-index: 2; pointer-events: none; animation: subtleFire 3s infinite alternate;\r\n      }\r\n      @keyframes subtleFire { from { opacity: 0.25; } to { opacity: 0.55; } }\r\n\r\n      /* [수정] 헤더: clamp를 이용한 반응형 간격 처리 */\r\n      .md8-header { \r\n        position: relative; z-index: 10; min-height: 140px;\r\n        background: rgba(0,0,0,0.8); display: flex; align-items: center; justify-content: center; \r\n        gap: clamp(12px, 3vw, 28px); border-bottom: 6px solid #ff1744; padding: 10px;\r\n      }\r\n\r\n      /* [수정] 미션 카드 & 이미지 최적화 */\r\n      .md-mission-card {\r\n        width: clamp(70px, 15vw, 100px); height: clamp(70px, 15vw, 100px);\r\n        background: #fff; border-radius: 22px; display: flex; align-items: center; justify-content: center;\r\n        border: 5px solid #fff; position: relative; transition: all 0.4s cubic-bezier(0.175, 0.885, 0.32, 1.275);\r\n      }\r\n      .md-mission-card img { width: 82%; height: 82%; object-fit: contain; }\r\n      .md-mission-card.active { border-color: #ffeb3b; transform: scale(1.25) rotate(5deg); box-shadow: 0 0 30px #ffeb3b; }\r\n      .md-mission-card.done { opacity: 0.25; filter: grayscale(100%); transform: scale(0.8); }\r\n\r\n      .md-role-tag { font-size: 16px; position: absolute; top: -12px; right: -12px; background: #fff; border-radius: 50%; width: 30px; height: 30px; display: grid; place-items: center; box-shadow: 0 2px 5px rgba(0,0,0,0.3); z-index:5; }\r\n\r\n      .md8-level-badge { position: absolute; top: 15px; left: 20px; background: #ff1744; color: #fff; padding: 5px 15px; border-radius: 15px; font-size: clamp(18px, 4vw, 24px); font-weight: 900; z-index: 100; border: 3px solid #fff; }\r\n\r\n      .md8-garage { flex: 1; display: grid; grid-template-columns: repeat(3, 1fr); gap: 15px; padding: 20px; z-index: 10; align-content: center; }\r\n      .md8-truck-btn { aspect-ratio: 1/1; background: #fff; border-radius: 25px; border: none; box-shadow: 0 10px 0 #888; display: flex; align-items: center; justify-content: center; position: relative; transition: transform 0.1s; overflow: visible; }\r\n      .md8-truck-btn img { width: 95%; height: 95%; object-fit: contain; }\r\n      \r\n      .md8-spotlight { position: absolute; inset: -10%; background: radial-gradient(circle, rgba(255,255,255,0.5) 0%, transparent 70%); opacity: 0; transition: opacity 0.2s; pointer-events: none; }\r\n      .md8-truck-btn.touch-active .md8-spotlight { opacity: 1; }\r\n      .md8-truck-btn.touch-active { transform: translateY(8px); box-shadow: 0 2px 0 #888; }\r\n\r\n      /* [복구] 쉐이크 애니메이션 */\r\n      .md-shake { animation: mdShake 0.45s linear; }\r\n      @keyframes mdShake {\r\n        0%, 100% { transform: translateX(0); }\r\n        10%, 30%, 50%, 70%, 90% { transform: translateX(-8px); }\r\n        20%, 40%, 60%, 80% { transform: translateX(8px); }\r\n      }\r\n\r\n      /* [수정] 엔딩 화면 버튼 최적화 */\r\n      #restartBtn { min-width: 220px; margin-top: 20px; padding: 15px 40px; font-size: 24px; border-radius: 30px; background: #ff1744; color: #fff; border: none; box-shadow: 0 8px 0 #b71c1c; font-weight: 900; }\r\n\r\n      .water-drop { position: absolute; width: 14px; height: 14px; background: #4fc3f7; border-radius: 50%; pointer-events: none; z-index: 1000; animation: waterFly 0.7s ease-out forwards; }\r\n      @keyframes waterFly { to { transform: translate(var(--tx), var(--ty)) scale(0); opacity: 0; } }\r\n\r\n      @media (min-width: 768px) {\r\n        .md8-garage { gap: 30px; padding: 40px; max-width: 900px; margin: 0 auto; }\r\n        .md8-header { min-height: 180px; gap: 30px; }\r\n      }\r\n    `;\r\n    document.head.appendChild(s);\r\n  }\r\n\r\n  /* [수정] 모바일 파티클 최적화 */\r\n  function shootWater(x, y, isSuper = false) {\r\n    const isMobile = window.innerWidth < 768;\r\n    const count = isSuper ? (isMobile ? 22 : 35) : (isMobile ? 12 : 18);\r\n    for (let i = 0; i < count; i++) {\r\n      const drop = document.createElement('div');\r\n      drop.className = 'water-drop';\r\n      drop.style.left = x + 'px'; drop.style.top = y + 'px';\r\n      drop.style.setProperty('--tx', (Math.random() * (isSuper ? 400 : 200) - (isSuper ? 200 : 100)) + 'px');\r\n      drop.style.setProperty('--ty', (Math.random() * -300 - 50) + 'px');\r\n      state.container.appendChild(drop);\r\n      setTimeout(() => drop.remove(), 700);\r\n    }\r\n  }\r\n\r\n  async function startRound() {\r\n    if (state.destroyed) return;\r\n    \r\n    // [수정] 안전한 상태 초기화\r\n    state.isBusy = false;\r\n    state.userIndex = 0;\r\n\r\n    if (state.allTrucks.length === 0) {\r\n      const res = await fetch(FIRE_DATA); \r\n      state.allTrucks = await res.json();\r\n    }\r\n    const missionCount = Math.min(state.currentLevel + 1, 5);\r\n    state.mission = [...state.allTrucks].sort(() => 0.5 - Math.random()).slice(0, missionCount);\r\n    \r\n    render();\r\n\r\n    // [복구] 시작 음성 가이드\r\n    if (state.options.speakGuide) {\r\n      state.options.speakGuide(`레벨 ${state.currentLevel}! 순서대로 출동하자!`, true);\r\n    }\r\n  }\r\n\r\n  function render() {\r\n    if (state.destroyed || !state.container) return;\r\n    state.container.innerHTML = `\r\n      <div class=\"md8-root\">\r\n        <div class=\"md8-city-bg\"></div>\r\n        <div class=\"md8-fire-overlay\"></div>\r\n        <div class=\"md8-level-badge\">LEVEL ${state.currentLevel}</div>\r\n        <div class=\"md8-header\">\r\n          ${state.mission.map((m, i) => `\r\n            <div class=\"md-mission-card ${i === state.userIndex ? 'active' : (i < state.userIndex ? 'done' : '')}\">\r\n              <div class=\"md-role-tag\">${ROLE_ICONS[m.id] || '🚒'}</div>\r\n              <img src=\"${m.file}\">\r\n            </div>\r\n          `).join(' <span style=\"color:#fff; font-size:24px;\">▶</span> ')}\r\n        </div>\r\n        <div class=\"md8-garage\">\r\n          ${state.allTrucks.slice(0, 9).map(t => `\r\n            <button class=\"md8-truck-btn\" data-id=\"${t.id}\">\r\n              <div class=\"md8-spotlight\"></div>\r\n              <img src=\"${t.file}\">\r\n            </button>\r\n          `).join('')}\r\n        </div>\r\n      </div>\r\n    `;\r\n    state.container.querySelectorAll('.md8-truck-btn').forEach(btn => {\r\n      btn.onclick = (e) => handleTouch(btn.dataset.id, btn, e);\r\n    });\r\n  }\r\n\r\n  function handleTouch(id, el, e) {\r\n    if (state.isBusy || state.destroyed) return;\r\n\r\n    el.classList.add('touch-active');\r\n    setTimeout(() => el.classList.remove('touch-active'), 280);\r\n\r\n    const target = state.mission[state.userIndex];\r\n\r\n    if (id === target.id) {\r\n      state.userIndex++;\r\n      state.combo++;\r\n      const isSuper = state.combo >= 2; // [수정] 4살 추천 밸런스\r\n      shootWater(e.clientX, e.clientY, isSuper);\r\n      if (navigator.vibrate) navigator.vibrate(isSuper ? 150 : 80);\r\n\r\n      const msg = isSuper ? \"초강력!! \" : \"\";\r\n      if (state.options.speakGuide) {\r\n        state.options.speakGuide(`${msg}${target.name_ko} 출동! ${target.sound_ko || ''}`, true);\r\n      }\r\n      \r\n      if (state.userIndex >= state.mission.length) {\r\n        state.isBusy = true;\r\n        setTimeout(finishRound, 700);\r\n      } else {\r\n        setTimeout(render, 550);\r\n      }\r\n    } else {\r\n      state.combo = 0;\r\n      if (state.options.speakGuide) state.options.speakGuide(\"아니야! 다시 봐보자!\", true);\r\n      if (navigator.vibrate) navigator.vibrate([40, 60, 40]);\r\n      \r\n      const root = state.container.querySelector('.md8-root');\r\n      if (root) {\r\n        root.classList.add('md-shake');\r\n        setTimeout(() => root.classList.remove('md-shake'), 450);\r\n      }\r\n    }\r\n  }\r\n\r\n  /* [수정] 명시적 상태 관리 및 애니메이션 최적화 */\r\n  function finishRound() {\r\n    if (state.destroyed) return;\r\n    \r\n    state.combo = 0;\r\n    state.isBusy = true; \r\n    \r\n    if (state.options.fireConfetti) state.options.fireConfetti();\r\n    if (state.options.gainExp) state.options.gainExp(25 + state.currentLevel * 18);\r\n\r\n    const clearedLevel = state.currentLevel;\r\n\r\n    if (clearedLevel === 8) {\r\n        showEnding();\r\n        return;\r\n    }\r\n\r\n    state.currentLevel++;\r\n    if (state.options.speakGuide) {\r\n      state.options.speakGuide(`와아아! ${clearedLevel}레벨 클리어!! 다음 레벨 출동!`, true);\r\n    }\r\n\r\n    const trucks = state.container.querySelectorAll('.md8-truck-btn');\r\n    trucks.forEach((btn, i) => {\r\n      setTimeout(() => {\r\n        btn.style.transition = '1.05s cubic-bezier(0.55, 0, 1, 1)';\r\n        btn.style.transform = 'translateX(200vw) scale(1.55) rotate(22deg)';\r\n      }, i * 70);\r\n    });\r\n\r\n    setTimeout(startRound, 2750);\r\n  }\r\n\r\n  /* [수정] 엔딩 후 재시작 로직 강화 */\r\n  function showEnding() {\r\n    state.isBusy = true;\r\n    state.combo = 0;\r\n    state.container.innerHTML = `\r\n      <div class=\"md8-root\" style=\"justify-content:center; align-items:center; text-align:center; color:#fff;\">\r\n        <div class=\"md8-city-bg\"></div>\r\n        <div style=\"z-index:100;\">\r\n          <h1 style=\"font-size: clamp(32px, 8vw, 52px); color: gold; text-shadow:0 0 30px red;\">🏆 전설의 시현 본부장 🏆</h1>\r\n          <p style=\"font-size: clamp(18px, 4vw, 26px);\">시현이가 모든 불을 다 껐어요!</p>\r\n          <div style=\"font-size: 80px; margin: 20px 0;\">🚒🔥🚑🚓</div>\r\n          <button id=\"restartBtn\">다시 출동! 🔄</button>\r\n        </div>\r\n      </div>\r\n    `;\r\n    if (state.options.speakGuide) state.options.speakGuide(\"시현 본부장님 만세! 당신은 최고의 소방 영웅입니다!\", true);\r\n    \r\n    document.getElementById('restartBtn').onclick = () => { \r\n      state.currentLevel = 1; \r\n      state.combo = 0;\r\n      state.isBusy = false;\r\n      startRound(); \r\n    };\r\n  }\r\n\r\n  function destroy() {\r\n    state.destroyed = true;\r\n    if (state.container) state.container.innerHTML = '';\r\n    state.container = null;\r\n  }\r\n\r\n  window.SihyeonGames = window.SihyeonGames || {};\r\n  window.SihyeonGames[GAME_KEY] = { \r\n    render: (c, o) => { state.container=c; state.options=o; state.destroyed=false; injectStyle(); startRound(); }, \r\n    destroy \r\n  };\r\n})();"
        }
    ]
}